Topsis/102103612.py
Topsis/__init__.py
Topsis_Kushagre_102103612-1.0.0.dist-info/LICENSE.unknown
Topsis_Kushagre_102103612-1.0.0.dist-info/METADATA
Topsis_Kushagre_102103612-1.0.0.dist-info/WHEEL
Topsis_Kushagre_102103612-1.0.0.dist-info/entry_points.txt
Topsis_Kushagre_102103612-1.0.0.dist-info/top_level.txt
Topsis_Kushagre_102103612-1.0.0.dist-info/RECORD
