Metadata-Version: 2.1
Name: Topsis-Kushagre-102103612
Version: 1.0.0
Summary: Topsis
Home-page: https://github.com/Kushagrekaushik/Topsis-Implementation
Author: Kushagre Kaushik
Author-email: Kushagrekaushik2003@gmail.com
License: MIT
Classifier: License :: OSI Approved :: MIT License
Classifier: Programming Language :: Python :: 3.6
Classifier: Programming Language :: Python :: 3.7
Classifier: Programming Language :: Python :: 3.8
License-File: LICENSE.unknown
